flowsom/__init__.py
flowsom/main.py
flowsom/io/__init__.py
flowsom/io/read_fcs.py
flowsom/models/__init__.py
flowsom/models/_som.py
flowsom/models/base_cluster_estimator.py
flowsom/models/base_flowsom_estimator.py
flowsom/models/batch_flowsom_estimator.py
flowsom/models/consensus_cluster.py
flowsom/models/flowsom_estimator.py
flowsom/models/numpy_numba.py
flowsom/models/pyFlowSOM_som_estimator.py
flowsom/models/pyflowsom_estimator.py
flowsom/models/som_estimator.py
flowsom/models/batch/__init__.py
flowsom/models/batch/_som.py
flowsom/models/batch/som_estimator.py
flowsom/pl/__init__.py
flowsom/pl/_plot_helper_functions.py
flowsom/pl/plot_functions.py
flowsom/pp/__init__.py
flowsom/pp/fcs_functions.py
flowsom/tl/__init__.py
flowsom/tl/getter_functions.py
flowsom-0.2.2.dist-info/METADATA
flowsom-0.2.2.dist-info/WHEEL
flowsom-0.2.2.dist-info/licenses/LICENSE
flowsom-0.2.2.dist-info/RECORD
