Metadata-Version: 2.4
Name: flowsom
Version: 0.2.2
Summary: The complete FlowSOM package known from R, now available in Python!
Project-URL: Documentation, https://flowsom.readthedocs.io/en/latest/
Project-URL: Home-page, https://github.com/saeyslab/FlowSOM_Python
Project-URL: Source, https://github.com/saeyslab/FlowSOM_Python
Author-email: Artuur Couckuyt <Artuur.Couckuyt@ugent.be>, Benjamin Rombaut <Benjamin.Rombaut@ugent.be>, Yvan Saeys <Yvan.Saeys@UGent.be>, Sofie Van Gassen <Sofie.VanGassen@UGent.be>
Maintainer-email: Artuur Couckuyt <Artuur.Couckuyt@ugent.be>, Benjamin Rombaut <Benjamin.Rombaut@ugent.be>, Yvan Saeys <Yvan.Saeys@UGent.be>, Sofie Van Gassen <Sofie.VanGassen@UGent.be>
License:                     GNU GENERAL PUBLIC LICENSE
License-File: LICENSE
Classifier: Programming Language :: Python :: 3 :: Only
Classifier: Programming Language :: Python :: 3.10
Classifier: Programming Language :: Python :: 3.11
Classifier: Programming Language :: Python :: 3.12
Classifier: Programming Language :: Python :: 3.13
Requires-Python: >=3.10
Requires-Dist: anndata
Requires-Dist: igraph
Requires-Dist: loguru
Requires-Dist: matplotlib
Requires-Dist: mudata
Requires-Dist: numba
Requires-Dist: numpy
Requires-Dist: pandas
Requires-Dist: readfcs
Requires-Dist: scanpy
Requires-Dist: scikit-learn
Requires-Dist: scipy
Requires-Dist: seaborn
Requires-Dist: session-info2
Provides-Extra: dev
Requires-Dist: pre-commit; extra == 'dev'
Requires-Dist: twine>=4.0.2; extra == 'dev'
Provides-Extra: doc
Requires-Dist: docutils!=0.18.*,!=0.19.*,>=0.8; extra == 'doc'
Requires-Dist: ipykernel; extra == 'doc'
Requires-Dist: ipython; extra == 'doc'
Requires-Dist: myst-nb>=1.1; extra == 'doc'
Requires-Dist: pandas; extra == 'doc'
Requires-Dist: pytometry>=0.1.5; extra == 'doc'
Requires-Dist: setuptools; extra == 'doc'
Requires-Dist: sphinx-autodoc-typehints; extra == 'doc'
Requires-Dist: sphinx-book-theme>=1; extra == 'doc'
Requires-Dist: sphinx-copybutton; extra == 'doc'
Requires-Dist: sphinx-tabs; extra == 'doc'
Requires-Dist: sphinx>=4; extra == 'doc'
Requires-Dist: sphinxcontrib-bibtex>=1; extra == 'doc'
Requires-Dist: sphinxext-opengraph; extra == 'doc'
Provides-Extra: test
Requires-Dist: coverage; extra == 'test'
Requires-Dist: pytest; extra == 'test'
